Metadata-Version: 1.1
Name: django-admin-auto-tests
Version: 0.1.2
Summary: Package description
